pfpy/__init__.py
pfpy/py.typed
pfpy/auth/__init__.py
pfpy/auth/parsed_header.py
pfpy/auth/parsed_url.py
pfpy/auth/utils.py
pfpy/types/__init__.py
pfpy/types/parsed_signature_header.py
ma_kyc_ri_pfpy-0.1.6.dist-info/METADATA
ma_kyc_ri_pfpy-0.1.6.dist-info/WHEEL
ma_kyc_ri_pfpy-0.1.6.dist-info/top_level.txt
ma_kyc_ri_pfpy-0.1.6.dist-info/RECORD
